aesthema/__init__.py
aesthema/colormaps.py
aesthema/colors.py
aesthema-0.1.1.dist-info/LICENSE
aesthema-0.1.1.dist-info/METADATA
aesthema-0.1.1.dist-info/WHEEL
aesthema-0.1.1.dist-info/top_level.txt
aesthema-0.1.1.dist-info/RECORD
