Metadata-Version: 2.1
Name: aesthema
Version: 0.1.1
Summary: Modern & visually appealing colormaps for Matplotlib
Author: jspieler
License: MIT
Classifier: Programming Language :: Python :: 3
Classifier: License :: OSI Approved :: MIT License
Requires-Python: >=3.8
License-File: LICENSE
Requires-Dist: cycler
Requires-Dist: matplotlib
Provides-Extra: linting
Requires-Dist: pylint ; extra == 'linting'
Requires-Dist: mypy ; extra == 'linting'
Provides-Extra: testing
Requires-Dist: numpy ; extra == 'testing'
